
[

    { "x":180.64, "y":305.35, "width":31.16,  "height":194.63 },
    { "x":0.0,    "y":0.0,    "width":595.54, "height":305.35 },
    { "x":0.0,    "y":305.35, "width":180.64, "height":194.63 },
    { "x":211.8,  "y":305.35, "width":383.73, "height":194.63 },
    { "x":0.0,    "y":499.99, "width":595.54, "height":294.4  },
    { "x":286.6,  "y":506.64, "width":17.67,  "height":107.49 },
    { "x":0.0,    "y":499.99, "width":595.54, "height":6.65   },
    { "x":0.0,    "y":506.64, "width":286.6,  "height":107.49 },
    { "x":304.28, "y":506.64, "width":291.25, "height":107.49 },
    { "x":0.0,    "y":614.14, "width":595.54, "height":180.25 },
    { "x":286.62, "y":614.18, "width":17.65,  "height":96.81  },
    { "x":0.0,    "y":614.14, "width":595.54, "height":0.04   },
    { "x":0.0,    "y":614.18, "width":286.62, "height":96.81  },
    { "x":304.27, "y":614.18, "width":291.26, "height":96.81  },
    { "x":0.0,    "y":710.99, "width":595.54, "height":83.4   }

]
